<?xml version='1.0' encoding='utf-8'?>
<TextureAtlas imagePath="pamtrigf.png"><SubTexture name="idle0000" x="219" y="0" width="191" height="431" frameX="-197" frameY="0" frameWidth="580" frameHeight="520" />
<SubTexture name="idle0001" x="0" y="432" width="198" height="430" frameX="-190" frameY="0" frameWidth="580" frameHeight="520" />
<SubTexture name="idle0002" x="0" y="862" width="232" height="423" frameX="-169" frameY="-9" frameWidth="580" frameHeight="520" />
<SubTexture name="idle0003" x="0" y="432" width="198" height="430" frameX="-190" frameY="0" frameWidth="580" frameHeight="520" />
<SubTexture name="idle0004" x="219" y="0" width="191" height="431" frameX="-197" frameY="0" frameWidth="580" frameHeight="520" />
<SubTexture name="idle0005" x="1278" y="0" width="205" height="425" frameX="-194" frameY="-9" frameWidth="580" frameHeight="520" />
<SubTexture name="idle0006" x="649" y="862" width="246" height="404" frameX="-171" frameY="-30" frameWidth="580" frameHeight="520" />
<SubTexture name="idle0007" x="1278" y="0" width="205" height="425" frameX="-194" frameY="-9" frameWidth="580" frameHeight="520" />
<SubTexture name="idle0008" x="219" y="0" width="191" height="431" frameX="-197" frameY="0" frameWidth="580" frameHeight="520" />
<SubTexture name="left0000" x="642" y="432" width="227" height="429" frameX="-180" frameY="0" frameWidth="580" frameHeight="520" />
<SubTexture name="left0001" x="410" y="0" width="219" height="431" frameX="-185" frameY="0" frameWidth="580" frameHeight="520" />
<SubTexture name="left0002" x="0" y="0" width="219" height="432" frameX="-186" frameY="0" frameWidth="580" frameHeight="520" />
<SubTexture name="left0003" x="410" y="0" width="219" height="431" frameX="-185" frameY="0" frameWidth="580" frameHeight="520" />
<SubTexture name="left0004" x="642" y="432" width="227" height="429" frameX="-180" frameY="0" frameWidth="580" frameHeight="520" />
<SubTexture name="right0000" x="198" y="432" width="225" height="430" frameX="-183" frameY="0" frameWidth="580" frameHeight="520" />
<SubTexture name="right0001" x="629" y="0" width="219" height="431" frameX="-183" frameY="0" frameWidth="580" frameHeight="520" />
<SubTexture name="right0002" x="423" y="432" width="219" height="430" frameX="-183" frameY="0" frameWidth="580" frameHeight="520" />
<SubTexture name="right0003" x="629" y="0" width="219" height="431" frameX="-183" frameY="0" frameWidth="580" frameHeight="520" />
<SubTexture name="right0004" x="198" y="432" width="225" height="430" frameX="-183" frameY="0" frameWidth="580" frameHeight="520" />
<SubTexture name="up0000" x="459" y="862" width="190" height="416" frameX="-196" frameY="-17" frameWidth="580" frameHeight="520" />
<SubTexture name="up0001" x="232" y="862" width="227" height="423" frameX="-176" frameY="-9" frameWidth="580" frameHeight="520" />
<SubTexture name="up0002" x="848" y="0" width="219" height="431" frameX="-187" frameY="0" frameWidth="580" frameHeight="520" />
<SubTexture name="up0003" x="232" y="862" width="227" height="423" frameX="-176" frameY="-9" frameWidth="580" frameHeight="520" />
<SubTexture name="up0004" x="459" y="862" width="190" height="416" frameX="-196" frameY="-17" frameWidth="580" frameHeight="520" />
<SubTexture name="down0000" x="869" y="432" width="192" height="418" frameX="-195" frameY="-15" frameWidth="580" frameHeight="520" />
<SubTexture name="down0001" x="895" y="862" width="192" height="388" frameX="-196" frameY="-46" frameWidth="580" frameHeight="520" />
<SubTexture name="down0002" x="1087" y="862" width="192" height="355" frameX="-201" frameY="-80" frameWidth="580" frameHeight="520" />
<SubTexture name="down0003" x="895" y="862" width="192" height="388" frameX="-196" frameY="-46" frameWidth="580" frameHeight="520" />
<SubTexture name="down0004" x="869" y="432" width="192" height="418" frameX="-195" frameY="-15" frameWidth="580" frameHeight="520" />
<SubTexture name="cheer0000" x="1067" y="0" width="211" height="429" frameX="-185" frameY="-4" frameWidth="580" frameHeight="520" />
<SubTexture name="cheer0001" x="1278" y="425" width="192" height="423" frameX="-195" frameY="-9" frameWidth="580" frameHeight="520" />
<SubTexture name="cheer0002" x="1067" y="0" width="211" height="429" frameX="-185" frameY="-4" frameWidth="580" frameHeight="520" />
<SubTexture name="miss0000" x="1067" y="429" width="192" height="428" frameX="-197" frameY="0" frameWidth="580" frameHeight="520" />
</TextureAtlas>
