<?xml version='1.0' encoding='utf-8'?>
<TextureAtlas imagePath="SCARY Spongebob.png">
<SubTexture name="SCARY Spongebob idle0000" x="0" y="1893" width="529" height="555" frameX="-98" frameY="-138" frameWidth="720" frameHeight="720" />
<SubTexture name="SCARY Spongebob idle0001" x="2345" y="0" width="523" height="566" frameX="-104" frameY="-125" frameWidth="720" frameHeight="720" />
<SubTexture name="SCARY Spongebob idle0002" x="1762" y="1297" width="532" height="569" frameX="-97" frameY="-122" frameWidth="720" frameHeight="720" />
<SubTexture name="SCARY Spongebob left0000" x="1142" y="1297" width="620" height="570" frameX="0" frameY="-121" frameWidth="720" frameHeight="720" />
<SubTexture name="SCARY Spongebob left0001" x="532" y="1297" width="610" height="590" frameX="-39" frameY="-101" frameWidth="720" frameHeight="720" />
<SubTexture name="SCARY Spongebob left0002" x="1744" y="0" width="601" height="597" frameX="-52" frameY="-94" frameWidth="720" frameHeight="720" />
<SubTexture name="SCARY Spongebob down0000" x="529" y="1893" width="557" height="452" frameX="-86" frameY="-247" frameWidth="720" frameHeight="720" />
<SubTexture name="SCARY Spongebob down0001" x="1645" y="1893" width="560" height="407" frameX="-67" frameY="-290" frameWidth="720" frameHeight="720" />
<SubTexture name="SCARY Spongebob down0002" x="1086" y="1893" width="559" height="420" frameX="-63" frameY="-276" frameWidth="720" frameHeight="720" />
<SubTexture name="SCARY Spongebob right0000" x="0" y="686" width="609" height="611" frameX="-111" frameY="-81" frameWidth="720" frameHeight="720" />
<SubTexture name="SCARY Spongebob right0001" x="609" y="686" width="551" height="608" frameX="-109" frameY="-84" frameWidth="720" frameHeight="720" />
<SubTexture name="SCARY Spongebob right0002" x="1160" y="686" width="556" height="608" frameX="-108" frameY="-84" frameWidth="720" frameHeight="720" />
<SubTexture name="SCARY Spongebob up0000" x="0" y="0" width="568" height="686" frameX="-84" frameY="0" frameWidth="720" frameHeight="720" />
<SubTexture name="SCARY Spongebob up0001" x="568" y="0" width="587" height="663" frameX="-67" frameY="-26" frameWidth="720" frameHeight="720" />
<SubTexture name="SCARY Spongebob up0002" x="1155" y="0" width="589" height="659" frameX="-64" frameY="-32" frameWidth="720" frameHeight="720" />
<SubTexture name="SCARY Spongebob red eye idle0000" x="0" y="1297" width="532" height="596" frameX="-97" frameY="-95" frameWidth="720" frameHeight="720" />
<SubTexture name="SCARY Spongebob red eye idle0001" x="1744" y="597" width="529" height="597" frameX="-95" frameY="-95" frameWidth="720" frameHeight="720" />
</TextureAtlas>
