{
	"storyName": "kids are getting eaten",
	"difficulties": "Hard",
	"hideFreeplay": false,
	"weekBackground": "bouncehouse",
	"freeplayColor": [
		146,
		113,
		253
	],
	"weekBefore": "tutorial",
	"startUnlocked": true,
	"weekCharacters": [
		"",
		"",
		""
	],
	"songs": [
		[
			"inflatable nightmare",
			"bouncyhouse",
			[
				174,
				156,
				84
			]
		],
		[
			"feed him",
			"bouncyhouse",
			[
				174,
				156,
				84
			]
		]
	],
	"hideStoryMode": false,
	"weekName": "bouncy house spongebob",
	"hiddenUntilUnlocked": false
}